{
    "prepare_queue": {
        "installed": [],
        "uninstalled": []
    },
    "config_munge": {
        "files": {}
    },
    "installed_plugins": {
        "cordova-plugin-statusbar": {
            "PACKAGE_NAME": "com.ar.granhotelverona"
        },
        "phonegap-plugin-push": {
            "SENDER_ID": "898486557686",
            "PACKAGE_NAME": "com.ar.granhotelverona"
        },
        "cordova-plugin-console": {
            "PACKAGE_NAME": "com.ar.granhotelverona"
        },
        "cordova-plugin-dialogs": {
            "PACKAGE_NAME": "com.ar.granhotelverona"
        },
        "cordova-plugin-whitelist": {
            "PACKAGE_NAME": "com.ar.granhotelverona"
        },
        "cordova-plugin-fcm": {
            "PACKAGE_NAME": "com.ar.granhotelverona"
        },
        "cordova-plugin-firebase": {
            "PACKAGE_NAME": "com.ar.granhotelverona"
        },
        "cordova-plugin-media": {
            "PACKAGE_NAME": "com.ar.granhotelverona"
        },
        "cordova-plugin-device": {
            "PACKAGE_NAME": "com.ar.granhotelverona"
        },
        "cordova-plugin-x-socialsharing": {
            "PACKAGE_NAME": "com.ar.granhotelverona"
        },
        "cordova-plugin-inappbrowser": {
            "PACKAGE_NAME": "com.ar.granhotelverona"
        }
    },
    "dependent_plugins": {
        "cordova-plugin-file": {
            "PACKAGE_NAME": "com.ar.granhotelverona"
        },
        "es6-promise-plugin": {
            "PACKAGE_NAME": "com.ar.granhotelverona"
        }
    }
}